crandom.py
complex_random-0.9.0.dist-info/LICENSE
complex_random-0.9.0.dist-info/METADATA
complex_random-0.9.0.dist-info/WHEEL
complex_random-0.9.0.dist-info/top_level.txt
complex_random-0.9.0.dist-info/RECORD
