Metadata-Version: 2.1
Name: complex-random
Version: 0.9.0
Summary: A package for only the most basic complex random sampling.
Home-page: https://github.com/goessl/complex-random
Author: Sebastian Gössl
Author-email: goessl@student.tugraz.at
License: MIT
Classifier: Programming Language :: Python :: 3.7
Classifier: License :: OSI Approved :: MIT License
Classifier: Operating System :: OS Independent
Requires-Python: >=3.7
License-File: LICENSE
Requires-Dist: numpy
